notionsnapshot/__init__.py
notionsnapshot/__main__.py
notionsnapshot/argparser.py
notionsnapshot/driver.py
notionsnapshot/injections/injection.css
notionsnapshot/injections/injection.js
notionsnapshot/logger.py
notionsnapshot-0.1.0.dist-info/LICENSE
notionsnapshot-0.1.0.dist-info/METADATA
notionsnapshot-0.1.0.dist-info/WHEEL
notionsnapshot-0.1.0.dist-info/RECORD
